gcp_pilot/__init__.py
gcp_pilot/api_gateway.py
gcp_pilot/api_key.py
gcp_pilot/app_engine.py
gcp_pilot/base.py
gcp_pilot/big_query.py
gcp_pilot/build.py
gcp_pilot/calendar.py
gcp_pilot/chats.py
gcp_pilot/datastore.py
gcp_pilot/datastream.py
gcp_pilot/directory.py
gcp_pilot/dns.py
gcp_pilot/drive.py
gcp_pilot/error_reporting.py
gcp_pilot/exceptions.py
gcp_pilot/functions.py
gcp_pilot/healthcare.py
gcp_pilot/iam.py
gcp_pilot/iap.py
gcp_pilot/identity_platform.py
gcp_pilot/logging.py
gcp_pilot/mocker.py
gcp_pilot/monitoring.py
gcp_pilot/people.py
gcp_pilot/pubsub.py
gcp_pilot/resource.py
gcp_pilot/run.py
gcp_pilot/scheduler.py
gcp_pilot/secret_manager.py
gcp_pilot/service_usage.py
gcp_pilot/sheets.py
gcp_pilot/source.py
gcp_pilot/speech.py
gcp_pilot/sql.py
gcp_pilot/storage.py
gcp_pilot/tasks.py
gcp_pilot/factories/__init__.py
gcp_pilot/factories/identity_platform.py
gcp_pilot/firestore/__init__.py
gcp_pilot/firestore/atomic.py
gcp_pilot/firestore/document.py
gcp_pilot/firestore/exceptions.py
gcp_pilot/firestore/factory.py
gcp_pilot/firestore/fqn.py
gcp_pilot/firestore/manager.py
gcp_pilot/firestore/operations.py
gcp_pilot/firestore/paginator.py
gcp_pilot/firestore/query.py
gcp_pilot/firestore/subcollection.py
gcp_pilot-1.39.0.dist-info/METADATA
gcp_pilot-1.39.0.dist-info/WHEEL
gcp_pilot-1.39.0.dist-info/licenses/LICENSE.md
gcp_pilot-1.39.0.dist-info/RECORD
