Metadata-Version: 2.4
Name: gcp-pilot
Version: 1.39.0
Summary: Google Cloud Platform Friendly Pilot
Author-email: Joao Daher <joao@daher.dev>
Maintainer: Rodolfo Stangherlin, Diego Freire, Guilherme Araujo, Lucas Gomide
License-File: LICENSE.md
Keywords: firestore orm,gcp,google cloud python
Requires-Python: >=3.11
Requires-Dist: factory-boy>=3.3.1
Requires-Dist: google-api-python-client>=2.154.0
Requires-Dist: pytz>=2024.2
Requires-Dist: tenacity>=9.0.0
Provides-Extra: bigquery
Requires-Dist: google-cloud-bigquery>=3.27.0; extra == 'bigquery'
Requires-Dist: google-cloud-storage>=2.19.0; extra == 'bigquery'
Provides-Extra: build
Requires-Dist: google-cloud-build>=3.27.1; extra == 'build'
Provides-Extra: datastore
Requires-Dist: google-cloud-datastore>=2.20.1; extra == 'datastore'
Requires-Dist: pydantic>=2.10.3; extra == 'datastore'
Provides-Extra: dns
Requires-Dist: google-cloud-dns>=0.35.0; extra == 'dns'
Provides-Extra: firestore
Requires-Dist: google-cloud-firestore>=2.20.1; extra == 'firestore'
Requires-Dist: pydantic>=2.10.3; extra == 'firestore'
Provides-Extra: healthcare
Requires-Dist: fhir-resources>=7.1.0; extra == 'healthcare'
Provides-Extra: iam
Requires-Dist: google-cloud-iam>=2.16.1; extra == 'iam'
Provides-Extra: monitoring
Requires-Dist: google-cloud-error-reporting>=1.11.1; extra == 'monitoring'
Requires-Dist: google-cloud-logging>=3.11.3; extra == 'monitoring'
Provides-Extra: pubsub
Requires-Dist: google-cloud-pubsub>=2.27.1; extra == 'pubsub'
Provides-Extra: secret
Requires-Dist: google-cloud-secret-manager>=2.21.1; extra == 'secret'
Provides-Extra: sheets
Requires-Dist: gspread>=6.1.4; extra == 'sheets'
Provides-Extra: speech
Requires-Dist: google-cloud-speech>=2.28.1; extra == 'speech'
Provides-Extra: storage
Requires-Dist: google-cloud-storage>=2.19.0; extra == 'storage'
Provides-Extra: tasks
Requires-Dist: google-cloud-scheduler>=2.14.1; extra == 'tasks'
Requires-Dist: google-cloud-tasks>=2.17.1; extra == 'tasks'
